{"list":[{"type":"sawblade","id":257,"onCC":271,"pos":{"x":29.140717280422457,"y":32.243125253733204},"angle":659.4800083777152,"tag":"i5","args":{"size":2},"welds":[{"other":270,"index":0,"pos":{"x":0,"y":0}}]},{"type":"spikes","id":256,"onCC":null,"pos":{"x":-18.61520435547038,"y":-141.5835813716871},"angle":1.7586317788880845,"tag":"GY","args":{"size":2,"pike":true},"welds":[]},{"type":"detacherlauncher","id":254,"onCC":null,"pos":{"x":110.91292042389803,"y":-167.44885591457285},"angle":1.2823280153480239,"tag":"fp","args":{"size":3,"launchKey":70},"welds":[{"other":260,"index":3,"pos":{"x":-1.0505249999999997,"y":0}}]},{"type":"detacherlauncher","id":247,"onCC":null,"pos":{"x":444.5606988891338,"y":82.65810358203599},"angle":3.0553883772832244,"tag":"KA","args":{"size":3,"launchKey":70},"welds":[{"other":245,"index":3,"pos":{"x":-1.0505249999999997,"y":0}}]},{"type":"spikes","id":248,"onCC":271,"pos":{"x":35.28802473670361,"y":19.908722256734176},"angle":45.41046875017342,"tag":"xS","args":{"size":2,"pike":false},"welds":[{"other":305,"index":0,"pos":{"x":0.02680831670273378,"y":0.10005}}]},{"type":"detacherlauncher","id":249,"onCC":null,"pos":{"x":-813.0641730564997,"y":-37.07102960666144},"angle":-20.06537366833119,"tag":"np","args":{"size":3,"launchKey":70},"welds":[]},{"type":"detacherlauncher","id":246,"onCC":null,"pos":{"x":-814.471933512955,"y":-247.51656283473622},"angle":1.9231212058972207,"tag":"Vr","args":{"size":3,"launchKey":70},"welds":[]},{"type":"sawblade","id":250,"onCC":271,"pos":{"x":34.82595470206727,"y":17.821080054417447},"angle":677.5438107027792,"tag":"fV","args":{"size":2},"welds":[{"other":296,"index":0,"pos":{"x":0,"y":0}}]},{"type":"spikes","id":245,"onCC":null,"pos":{"x":445.49064513996433,"y":82.57773907214955},"angle":4.822534244927483,"tag":"Bv","args":{"size":3,"pike":true},"welds":[{"other":247,"index":0,"pos":{"x":0.022847558316737373,"y":0.11486243222438174}}]},{"type":"hingehalf","id":251,"onCC":271,"pos":{"x":35.31076631770771,"y":26.343797893406826},"angle":39.645403594412336,"tag":"kg","args":{"rotKey":83,"size":2,"motor":true},"welds":[{"other":271,"index":1,"pos":{"x":1.0005,"y":0.50025}},{"other":271,"index":2,"pos":{"x":1.0005,"y":-0.50025}},{"other":266,"index":3,"pos":{"x":2.001,"y":0}}]},{"type":"detacherlauncher","id":252,"onCC":null,"pos":{"x":565.3219646711009,"y":-273.62121750877435},"angle":3.5363495956499054,"tag":"nJ","args":{"size":3,"launchKey":70},"welds":[]},{"type":"hingehalf","id":253,"onCC":271,"pos":{"x":35.31076631770701,"y":26.34379789341031},"angle":36.50381094082569,"tag":"An","args":{"rotKey":65,"size":2,"motor":true},"welds":[{"other":271,"index":1,"pos":{"x":1.0005,"y":0.50025}},{"other":271,"index":2,"pos":{"x":1.0005,"y":-0.50025}},{"other":267,"index":3,"pos":{"x":2.001,"y":0}}]},{"type":"sawblade","id":258,"onCC":null,"pos":{"x":-49.752283074630036,"y":-59.25535501618814},"angle":42.57966742655591,"tag":"fL","args":{"size":3},"welds":[]},{"type":"spikes","id":259,"onCC":null,"pos":{"x":475.25851563304866,"y":-312.15597622155815},"angle":-0.7805927139368145,"tag":"XH","args":{"size":3,"pike":true},"welds":[]},{"type":"spikes","id":260,"onCC":null,"pos":{"x":110.64737941644222,"y":-168.34370029056365},"angle":-3.2337114241873044,"tag":"i3","args":{"size":3,"pike":true},"welds":[{"other":254,"index":0,"pos":{"x":0.022847558316737373,"y":0.11486243222438174}}]},{"type":"spikes","id":261,"onCC":null,"pos":{"x":-196.52166591457635,"y":105.34686203677973},"angle":0.2193659046356796,"tag":"XE","args":{"size":3,"pike":true},"welds":[]},{"type":"spikes","id":262,"onCC":null,"pos":{"x":294.06615177078334,"y":-444.53101726845114},"angle":13.278345586596416,"tag":"ni","args":{"size":3,"pike":true},"welds":[{"other":264,"index":0,"pos":{"x":0.022847558316737373,"y":0.11486243222438174}}]},{"type":"spikes","id":263,"onCC":271,"pos":{"x":30.903043548614868,"y":31.032354917855436},"angle":53.25350663606601,"tag":"ZN","args":{"size":2,"pike":false},"welds":[{"other":301,"index":0,"pos":{"x":0.02680831670273378,"y":0.10005}}]},{"type":"detacherlauncher","id":264,"onCC":null,"pos":{"x":294.5263978212316,"y":-445.34307148888826},"angle":17.794385026131742,"tag":"BI","args":{"size":3,"launchKey":70},"welds":[{"other":262,"index":3,"pos":{"x":-1.0505249999999997,"y":0}}]},{"type":"detacherlauncher","id":265,"onCC":null,"pos":{"x":487.48991161197887,"y":-296.25498205664974},"angle":-9.75584606500889,"tag":"re","args":{"size":3,"launchKey":70},"welds":[]},{"type":"hingehalf","id":267,"onCC":271,"pos":{"x":37.88417764993811,"y":23.694843188356035},"angle":40.436280381990386,"tag":"Bu","args":{"rotKey":83,"size":2,"motor":false},"welds":[{"other":308,"index":1,"pos":{"x":1.0005,"y":0.50025}},{"other":308,"index":2,"pos":{"x":1.0005,"y":-0.50025}},{"other":253,"index":3,"pos":{"x":2.001,"y":0}}]},{"type":"hingehalf","id":266,"onCC":271,"pos":{"x":35.38438923054408,"y":30.036231162081382},"angle":35.71294765352183,"tag":"HL","args":{"rotKey":65,"size":2,"motor":false},"welds":[{"other":307,"index":1,"pos":{"x":1.0005,"y":0.50025}},{"other":307,"index":2,"pos":{"x":1.0005,"y":-0.50025}},{"other":251,"index":3,"pos":{"x":2.001,"y":0}}]},{"type":"spikes","id":255,"onCC":null,"pos":{"x":52.722916230533485,"y":-30.60928329819951},"angle":12.85100586638801,"tag":"s2","args":{"size":3,"pike":false},"welds":[]},{"type":"thruster","id":291,"onCC":271,"pos":{"x":31.574807791207178,"y":30.07614208863816},"angle":-0.41536786275965293,"tag":"rI","args":{"thrustKey":83,"size":1},"welds":[{"other":301,"index":0,"pos":{"x":0,"y":0.50025}}]},{"type":"thruster","id":293,"onCC":271,"pos":{"x":37.257328403986946,"y":25.497986348640037},"angle":44.357792574798985,"tag":"sk","args":{"thrustKey":39,"size":1},"welds":[{"other":271,"index":0,"pos":{"x":0,"y":0.50025}}]},{"type":"thruster","id":295,"onCC":null,"pos":{"x":14.715395532973961,"y":-77.59449243862716},"angle":-6.774690413935952,"tag":"Xe","args":{"thrustKey":38,"size":1},"welds":[]},{"type":"thruster","id":297,"onCC":271,"pos":{"x":44.60517932877436,"y":27.31907149206462},"angle":50.640977881978706,"tag":"F0","args":{"thrustKey":37,"size":2},"welds":[{"other":302,"index":0,"pos":{"x":0,"y":1.0005}}]},{"type":"thruster","id":298,"onCC":271,"pos":{"x":45.916386478717556,"y":29.449092001927845},"angle":45.92858890159402,"tag":"Gl","args":{"thrustKey":38,"size":2},"welds":[{"other":302,"index":0,"pos":{"x":0,"y":1.0005}}]},{"type":"sawmotor","id":269,"onCC":null,"pos":{"x":-16.128581960611367,"y":87.95654581715569},"angle":-18.315865820019216,"tag":"bY","args":{"size":2,"rotKey":71},"welds":[]},{"type":"thruster","id":273,"onCC":null,"pos":{"x":66.02438596841245,"y":-151.9051602253892},"angle":0.18444883819225433,"tag":"f9","args":{"thrustKey":39,"size":1},"welds":[]},{"type":"thruster","id":268,"onCC":271,"pos":{"x":41.09247109581216,"y":30.77379824429538},"angle":58.49495951595313,"tag":"LW","args":{"thrustKey":37,"size":2},"welds":[{"other":314,"index":0,"pos":{"x":0,"y":1.0005}}]},{"type":"laser","id":274,"onCC":271,"pos":{"x":38.75206889351966,"y":21.908588510457868},"angle":46.71946568917026,"tag":"uZ","args":{"fireKey":90},"welds":[{"other":303,"index":0,"pos":{"x":0,"y":-0.30015}}]},{"type":"laser","id":275,"onCC":271,"pos":{"x":34.79992863473305,"y":31.934216092723496},"angle":51.42091092147148,"tag":"R7","args":{"fireKey":90},"welds":[{"other":309,"index":0,"pos":{"x":0,"y":-0.30015}}]},{"type":"missile-launcher","id":276,"onCC":271,"pos":{"x":33.91727932067017,"y":26.332201597262817},"angle":39.6454035944143,"tag":"Zg","args":{"fireKey":32},"welds":[{"other":271,"index":0,"pos":{"x":0,"y":-0.30015}}]},{"type":"sawmotor","id":278,"onCC":null,"pos":{"x":-0.4548110918732464,"y":-69.4337429242583},"angle":-42.90928074673992,"tag":"tO","args":{"size":1,"rotKey":71},"welds":[]},{"type":"thruster","id":280,"onCC":271,"pos":{"x":36.57248441959342,"y":19.35895043201755},"angle":38.8654840551947,"tag":"BN","args":{"thrustKey":81,"size":1},"welds":[{"other":305,"index":0,"pos":{"x":0,"y":0.50025}}]},{"type":"thruster","id":281,"onCC":271,"pos":{"x":31.46683897438344,"y":32.310721240199776},"angle":40.425336633907634,"tag":"Px","args":{"thrustKey":81,"size":1},"welds":[{"other":301,"index":0,"pos":{"x":0,"y":0.50025}}]},{"type":"missile-launcher","id":282,"onCC":271,"pos":{"x":34.284196167839916,"y":25.40141038691379},"angle":39.645403594414304,"tag":"Z6","args":{"fireKey":32},"welds":[{"other":271,"index":0,"pos":{"x":0,"y":-0.30015}}]},{"type":"thruster","id":283,"onCC":271,"pos":{"x":36.15657786247771,"y":28.29035997968714},"angle":34.93301461402961,"tag":"vW","args":{"thrustKey":37,"size":1},"welds":[{"other":271,"index":0,"pos":{"x":0,"y":0.50025}}]},{"type":"thruster","id":284,"onCC":null,"pos":{"x":-55.368772411572564,"y":71.08544201206745},"angle":-17.94173728791069,"tag":"lp","args":{"thrustKey":38,"size":1},"welds":[]},{"type":"thruster","id":285,"onCC":271,"pos":{"x":45.18255278437781,"y":31.3106744226258},"angle":64.77814482313278,"tag":"wS","args":{"thrustKey":38,"size":2},"welds":[{"other":302,"index":0,"pos":{"x":0,"y":1.0005}}]},{"type":"thruster","id":286,"onCC":null,"pos":{"x":21.731550102308113,"y":-186.31045126701395},"angle":3.896715044161698,"tag":"td","args":{"thrustKey":37,"size":1},"welds":[]},{"type":"sawmotor","id":287,"onCC":null,"pos":{"x":-56.81521800296095,"y":-59.795646392162624},"angle":-109.38612060005875,"tag":"hN","args":{"size":2,"rotKey":71},"welds":[]},{"type":"thruster","id":288,"onCC":null,"pos":{"x":-55.28112800180262,"y":50.14659466007428},"angle":-0.8177139925061174,"tag":"Xj","args":{"thrustKey":38,"size":2},"welds":[]},{"type":"thruster","id":289,"onCC":null,"pos":{"x":14.948718229061273,"y":-78.90606599287025},"angle":-10.035048321328029,"tag":"LP","args":{"thrustKey":38,"size":1},"welds":[]},{"type":"thruster","id":279,"onCC":null,"pos":{"x":70.68058451845518,"y":-150.7506805122318},"angle":12.646422279480625,"tag":"ac","args":{"thrustKey":39,"size":1},"welds":[]},{"type":"thruster","id":290,"onCC":271,"pos":{"x":35.126592923887316,"y":21.066111535324627},"angle":-1.9752204414726102,"tag":"bd","args":{"thrustKey":83,"size":1},"welds":[{"other":305,"index":0,"pos":{"x":0,"y":0.50025}}]},{"type":"sawmotor","id":277,"onCC":null,"pos":{"x":49.326084736565576,"y":-69.81246224094379},"angle":-78.60462469112936,"tag":"nu","args":{"size":3,"rotKey":71},"welds":[]},{"type":"thruster","id":292,"onCC":271,"pos":{"x":42.77059509292507,"y":31.97302754380954},"angle":47.49938522838891,"tag":"TK","args":{"thrustKey":39,"size":2},"welds":[{"other":302,"index":0,"pos":{"x":0,"y":1.0005}}]},{"type":"sawmotor","id":270,"onCC":271,"pos":{"x":31.52082338279566,"y":31.193431664419702},"angle":40.42533663390842,"tag":"VA","args":{"size":2,"rotKey":71},"welds":[{"other":301,"index":0,"pos":{"x":1.0005,"y":0}},{"other":257,"index":3,"pos":{"x":2.6013,"y":0}}]},{"type":"thruster","id":294,"onCC":271,"pos":{"x":42.56013848449141,"y":27.050633402899322},"angle":52.211774208773534,"tag":"gW","args":{"thrustKey":39,"size":2},"welds":[{"other":313,"index":0,"pos":{"x":0,"y":1.0005}}]},{"type":"cc","id":271,"onCC":271,"pos":{"x":35.77616192288342,"y":26.527256316993896},"angle":36.50381094082445,"tag":"xK","args":{"aiStr":"{\r\n    init: function (ccblock) {\r\n\r\n        this.state = new Object();\r\n\r\n        // component = this.get(tag)\r\n        // this.each(function(component){ ... });\r\n        \r\n        this.mover = this.make_controller(\r\n            'movement',\r\n            {\r\n                comp: ccblock,\r\n                radius: 5,\r\n                charge: true\r\n            }\r\n        );\r\n        \r\n        this.sensor = this.make_sensor(\r\n            'radius',\r\n            {\r\n                comp: ccblock,\r\n                angle: [ -Math.PI/8, Math.PI/8 ],\r\n                distance: [ 0, 8 ],\r\n                enemy: true\r\n            }\r\n        )\r\n        \r\n        this.state.targetp = this.vec(0,0);\r\n\r\n    },\r\n\r\n    update: function (dt, keyDown) {\r\n        \r\n        if (BSWG.input.MOUSE('left')) {\r\n            this.state.targetp = this.mouse();\r\n        }\r\n        \r\n        this.mover.moveTo(\r\n            this.player_cc().p() || this.state.targetp,\r\n            keyDown,\r\n            BSWG.KEY.LEFT, BSWG.KEY.RIGHT,\r\n            BSWG.KEY.UP, BSWG.KEY.DOWN\r\n        );\r\n\r\n        keyDown[BSWG.KEY.G] = true;\r\n        keyDown[BSWG.KEY.Z] = true;\r\n        \r\n        if (this.sensor.found) {\r\n            keyDown[BSWG.KEY.A] = true;\r\n            keyDown[BSWG.KEY.Q] = true;\r\n        }\r\n        else {\r\n            keyDown[BSWG.KEY.S] = true;\r\n            keyDown[BSWG.KEY.SPACE] = true;\r\n        }\r\n        \r\n    }\r\n}"},"welds":[{"other":251,"index":0,"pos":{"x":-1.0005,"y":-1.0005}},{"other":253,"index":1,"pos":{"x":1.0005,"y":-1.0005}},{"other":251,"index":2,"pos":{"x":-1.0005,"y":0}},{"other":253,"index":3,"pos":{"x":1.0005,"y":0}},{"other":283,"index":4,"pos":{"x":-1.0005,"y":1.0005}},{"other":293,"index":5,"pos":{"x":1.0005,"y":1.0005}},{"other":276,"index":6,"pos":{"x":-0.50025,"y":-1.50075}},{"other":312,"index":7,"pos":{"x":-0.50025,"y":1.50075}},{"other":282,"index":8,"pos":{"x":0.50025,"y":-1.50075}},{"other":312,"index":9,"pos":{"x":0.50025,"y":1.50075}},{"other":312,"index":11,"pos":{"x":0,"y":1.50075}}]},{"type":"sawmotor","id":296,"onCC":271,"pos":{"x":35.849538671741044,"y":20.21253098367083},"angle":42.007076708783835,"tag":"Gp","args":{"size":2,"rotKey":71},"welds":[{"other":305,"index":0,"pos":{"x":1.0005,"y":0}},{"other":250,"index":3,"pos":{"x":2.6013,"y":0}}]},{"type":"thruster","id":272,"onCC":null,"pos":{"x":11.604797535885341,"y":-188.0113133632116},"angle":5.316551518940304,"tag":"ju","args":{"thrustKey":37,"size":1},"welds":[]},{"type":"block","id":309,"onCC":271,"pos":{"x":35.788117534127394,"y":30.95165658607069},"angle":45.13772561429189,"tag":"e1","args":{"width":2,"height":2,"armour":false,"triangle":0},"welds":[{"other":307,"index":0,"pos":{"x":-1.0005,"y":-0.50025}},{"other":307,"index":2,"pos":{"x":-1.0005,"y":0.50025}},{"other":275,"index":9,"pos":{"x":0.50025,"y":1.0005}}]},{"type":"block","id":307,"onCC":271,"pos":{"x":34.724812366757924,"y":29.780382601878532},"angle":38.854540307112295,"tag":"nK","args":{"width":1,"height":3,"armour":false,"triangle":0},"welds":[{"other":266,"index":0,"pos":{"x":-0.50025,"y":-1.0005}},{"other":309,"index":1,"pos":{"x":0.50025,"y":-1.0005}},{"other":266,"index":2,"pos":{"x":-0.50025,"y":0}},{"other":309,"index":3,"pos":{"x":0.50025,"y":0}},{"other":301,"index":7,"pos":{"x":0,"y":1.50075}}]},{"type":"block","id":301,"onCC":271,"pos":{"x":31.97853609478999,"y":30.991567512627537},"angle":38.854540307112785,"tag":"sh","args":{"width":1,"height":3,"armour":false,"triangle":0},"welds":[{"other":291,"index":2,"pos":{"x":-0.50025,"y":0}},{"other":263,"index":4,"pos":{"x":-0.50025,"y":1.0005}},{"other":281,"index":5,"pos":{"x":0.50025,"y":1.0005}},{"other":307,"index":6,"pos":{"x":0,"y":-1.50075}},{"other":270,"index":7,"pos":{"x":0,"y":1.50075}}]},{"type":"block","id":302,"onCC":271,"pos":{"x":43.68788721084971,"y":29.64604951793708},"angle":50.640977881978706,"tag":"AR","args":{"width":2,"height":3,"armour":false,"triangle":0},"welds":[{"other":298,"index":1,"pos":{"x":1.0005,"y":-1.0005}},{"other":310,"index":2,"pos":{"x":-1.0005,"y":0}},{"other":285,"index":5,"pos":{"x":1.0005,"y":1.0005}},{"other":297,"index":10,"pos":{"x":0,"y":-1.50075}},{"other":292,"index":11,"pos":{"x":0,"y":1.50075}}]},{"type":"block","id":303,"onCC":271,"pos":{"x":38.80396646888234,"y":23.301157046175756},"angle":48.290262015965155,"tag":"bz","args":{"width":2,"height":2,"armour":false,"triangle":0},"welds":[{"other":274,"index":3,"pos":{"x":1.0005,"y":0.50025}},{"other":308,"index":6,"pos":{"x":-0.50025,"y":-1.0005}},{"other":308,"index":8,"pos":{"x":0.50025,"y":-1.0005}}]},{"type":"block","id":300,"onCC":null,"pos":{"x":156.6220803778447,"y":-106.82663319760103},"angle":29.015099906584705,"tag":"eI","args":{"width":2,"height":3,"armour":false,"triangle":0},"welds":[{"other":299,"index":2,"pos":{"x":-1.0005,"y":0}},{"other":306,"index":3,"pos":{"x":1.0005,"y":0}}]},{"type":"block","id":304,"onCC":null,"pos":{"x":97.76815343148768,"y":30.45286419549756},"angle":-102.95501061987842,"tag":"Ci","args":{"width":1,"height":2,"armour":false,"triangle":1},"welds":[]},{"type":"block","id":299,"onCC":null,"pos":{"x":157.72956157351996,"y":-105.8138469596783},"angle":27.44430357978981,"tag":"jb","args":{"width":2,"height":1,"armour":false,"triangle":1},"welds":[{"other":300,"index":3,"pos":{"x":0,"y":0.50025}}]},{"type":"block","id":305,"onCC":271,"pos":{"x":36.046381742831166,"y":20.67242539314304},"angle":37.294687728399786,"tag":"wX","args":{"width":1,"height":3,"armour":false,"triangle":0},"welds":[{"other":248,"index":0,"pos":{"x":-0.50025,"y":-1.0005}},{"other":280,"index":1,"pos":{"x":0.50025,"y":-1.0005}},{"other":290,"index":2,"pos":{"x":-0.50025,"y":0}},{"other":296,"index":6,"pos":{"x":0,"y":-1.50075}},{"other":308,"index":7,"pos":{"x":0,"y":1.50075}}]},{"type":"block","id":306,"onCC":null,"pos":{"x":155.5145991821694,"y":-107.83941943552375},"angle":29.01509990658471,"tag":"VZ","args":{"width":1,"height":2,"armour":false,"triangle":1},"welds":[{"other":300,"index":2,"pos":{"x":-0.50025,"y":0}}]},{"type":"block","id":308,"onCC":271,"pos":{"x":37.2274401693755,"y":23.43179184997477},"angle":43.5778730355796,"tag":"pM","args":{"width":1,"height":3,"armour":false,"triangle":0},"welds":[{"other":267,"index":2,"pos":{"x":-0.50025,"y":0}},{"other":303,"index":3,"pos":{"x":0.50025,"y":0}},{"other":267,"index":4,"pos":{"x":-0.50025,"y":1.0005}},{"other":303,"index":5,"pos":{"x":0.50025,"y":1.0005}},{"other":305,"index":6,"pos":{"x":0,"y":-1.50075}}]},{"type":"block","id":310,"onCC":271,"pos":{"x":41.36090918497727,"y":28.72875740001247},"angle":-4.336893555842698,"tag":"qs","args":{"width":2,"height":3,"armour":false,"triangle":0},"welds":[{"other":313,"index":4,"pos":{"x":-1.0005,"y":1.0005}},{"other":314,"index":5,"pos":{"x":1.0005,"y":1.0005}},{"other":312,"index":7,"pos":{"x":-0.50025,"y":1.50075}},{"other":312,"index":9,"pos":{"x":0.50025,"y":1.50075}},{"other":302,"index":10,"pos":{"x":0,"y":-1.50075}},{"other":312,"index":11,"pos":{"x":0,"y":1.50075}}]},{"type":"block","id":311,"onCC":null,"pos":{"x":-94.77605153473115,"y":-91.08516284175299},"angle":1.651208910376503,"tag":"y7","args":{"width":1,"height":2,"armour":false,"triangle":1},"welds":[]},{"type":"block","id":312,"onCC":271,"pos":{"x":38.5685355539304,"y":27.62800685850309},"angle":49.07018155518369,"tag":"lJ","args":{"width":2,"height":3,"armour":false,"triangle":0},"welds":[{"other":314,"index":4,"pos":{"x":-1.0005,"y":1.0005}},{"other":313,"index":5,"pos":{"x":1.0005,"y":1.0005}},{"other":271,"index":6,"pos":{"x":-0.50025,"y":-1.50075}},{"other":310,"index":7,"pos":{"x":-0.50025,"y":1.50075}},{"other":271,"index":8,"pos":{"x":0.50025,"y":-1.50075}},{"other":310,"index":9,"pos":{"x":0.50025,"y":1.50075}},{"other":271,"index":10,"pos":{"x":0,"y":-1.50075}},{"other":310,"index":11,"pos":{"x":0,"y":1.50075}}]},{"type":"block","id":313,"onCC":271,"pos":{"x":40.69855606379339,"y":26.316799708559724},"angle":0.37549542454194185,"tag":"JL","args":{"width":2,"height":2,"armour":false,"triangle":0},"welds":[{"other":294,"index":5,"pos":{"x":1.0005,"y":0}},{"other":312,"index":7,"pos":{"x":-0.50025,"y":1.0005}},{"other":310,"index":9,"pos":{"x":0.50025,"y":1.0005}}]},{"type":"block","id":314,"onCC":271,"pos":{"x":39.230888675114144,"y":30.039964549955773},"angle":5.0878844049266405,"tag":"Jt","args":{"width":2,"height":2,"armour":false,"triangle":0},"welds":[{"other":312,"index":1,"pos":{"x":1.0005,"y":-0.50025}},{"other":310,"index":3,"pos":{"x":1.0005,"y":0.50025}},{"other":268,"index":11,"pos":{"x":0,"y":1.0005}}]}]}